{"locale":"en-GB","location":{"name":"Portland, Oregon, USA","latitude":45.5199,"longitude":-122.6821},"flip":"book","sentOn":"2017-07-11","sender":{"name":"Claire","uri":"https://www.instagram.com/claire.durrant88/"},"recipient":{"name":"JP","uri":"https://www.byjp.me"},"front":{"description":"An illustration of a naked, but booted, man and woman riding a tandem bike on a background of hearts.","transcription":{}},"back":{"transcription":{"text":"SHUT UP, JP.","annotations":[{"type":"locale","value":"en-US","start":0,"end":12}]},"secrets":[{"prehidden":true,"points":[[0.5798110393,0.5128771155],[0.9741422178,0.5128771155],[0.9741422178,0.6968359087],[0.5798110393,0.6968359087]]}]},"context":{"author":{"name":""},"description":""},"physical":{"frontSize":{"cmW":"2011/128","cmH":"1359/128","pxW":2011,"pxH":1359}}}
