{"locale":"en-GB","location":{"name":"Stockholm, Sweden","latitude":59.3289,"longitude":18.067},"flip":"book","sentOn":"2016-06-15","sender":{"name":"Claire","uri":"https://www.instagram.com/claire.durrant88/"},"recipient":{"name":"JP","uri":"https://www.byjp.me"},"front":{"description":"An aerial photograph of snow-covered Stockholm's harbours.","transcription":{}},"back":{"transcription":{"text":"HALL KÄFTEN, JP.","annotations":[{"type":"locale","value":"se-SE","start":0,"end":16}]},"secrets":[{"prehidden":true,"points":[[0.5751088534,0.5138369484],[0.9775036283999999,0.5138369484],[0.9775036283999999,0.7344801795],[0.5751088534,0.7344801795]]}]},"context":{"author":{"name":""},"description":""},"physical":{"frontSize":{"cmW":"689/32","cmH":"1337/128","pxW":2756,"pxH":1337}}}
