{"locale":"en-GB","location":{"name":"Stanley Park, Vancouver, Canada","lat":49.304,"long":-123.144},"flip":"book","sentOn":"2022-09-09","sender":{"name":"Claire","uri":"https://www.instagram.com/claire.durrant88/"},"recipient":{"name":"JP"},"front":{"description":"A photograph of a collection of detailed and colourful totem poles of different heights in Stanley Park. They are in front of verdant tall trees, and a rich blue sky."},"back":{"description":"Explanation text says: The Totem Poles in Stanley Park are a major tourist attraction.","transcription":"\u003cspan lang=\"en-CA\"\u003eShut up, JP\n\n(eh)\u003c/span\u003e\n","secrets":[[[0.5953991881,0.6036036036],[0.949481281,0.6036036036],[0.949481281,0.750965251],[0.5953991881,0.750965251]]]},"frontSize":{"cmW":"2217/128","cmH":"777/32","pxW":2217,"pxH":1554},"context":{"author":{"name":""},"description":""}}
